tiff2csv/TiffReader.py
tiff2csv/__init__.py
tiff2csv/__main__.py
tiff2csv-0.0.4.dist-info/LICENSE
tiff2csv-0.0.4.dist-info/METADATA
tiff2csv-0.0.4.dist-info/WHEEL
tiff2csv-0.0.4.dist-info/top_level.txt
tiff2csv-0.0.4.dist-info/RECORD
