Metadata-Version: 2.1
Name: tiff2csv
Version: 0.0.4
Summary: A lightweight python package for processing .tif image data files.
Home-page: https://github.com/alhermann/TIFF2Vox.git
Author: Alexander Hermann
Author-email: alexander.hermann@hzg.de
License: UNKNOWN
Platform: UNKNOWN
Classifier: Programming Language :: Python :: 3
Classifier: License :: OSI Approved :: MIT License
Classifier: Operating System :: OS Independent
Requires-Python: >=3.6
